{"cameraMode":{"drawMode":0,"name":"Shaded","section":"Shading Mode"},"sceneLighting":true,"audioPlay":false,"sceneViewState":{"m_AlwaysRefresh":false,"showFog":true,"showSkybox":true,"showFlares":true,"showImageEffects":true,"showParticleSystems":true,"showVisualEffectGraphs":true,"m_FxEnabled":true},"in2DMode":false,"pivot":{"x":45.391746520996097,"y":-22.24138069152832,"z":40.6832160949707},"rotation":{"x":-0.18289272487163545,"y":-0.38079848885536196,"z":0.07713298499584198,"w":-0.9031548500061035},"size":34.2969970703125,"orthographic":false}